<?xml version="1.0" encoding="UTF-8"?>

<framexml>
<data>

<!-- 1M2 -->
<text><![CDATA[<B>Services</B>]]></text>
<text><![CDATA[In cities and towns, there are groups of people who provide different services to help the people.]]></text>
<text><![CDATA[The <i>police</i> keep us and our properties safe. ]]></text>
<text><![CDATA[The <i>traffic police</i> maintain the flow of traffic on roads and also check if everyone is obeying the traffic rules.]]></text>
<text><![CDATA[The <i>firefighters</i> help put out dangerous fires. ]]></text>
<text><![CDATA[In hospitals and clinics, <i>doctors</i> and <i>nurses</i> treat the people who are ill or injured.]]></text>
<text><![CDATA[]]></text>

</data>
</framexml>